{"$otSharedSchema":"#/protocol/schemas/8","schemaVersion":8,"metadata":{"protocolName":"Robin Pixel Art","author":"Harry Smith - University of Bristol","description":"","created":1729597082090,"lastModified":1729598265214,"category":null,"subcategory":null,"tags":[]},"designerApplication":{"name":"opentrons/protocol-designer","version":"8.1.3","data":{"_internalAppBuildDate":"Wed, 24 Jul 2024 18:11:35 GMT","defaultValues":{"aspirate_mmFromBottom":1,"dispense_mmFromBottom":1,"touchTip_mmFromTop":-1,"blowout_mmFromTop":0},"pipetteTiprackAssignments":{"44539684-2a7a-4443-b90c-9886bb3b0e05":["opentrons/opentrons_96_tiprack_1000ul/1"]},"dismissedWarnings":{"form":["BELOW_PIPETTE_MINIMUM_VOLUME","BELOW_MIN_DISPOSAL_VOLUME"],"timeline":[]},"ingredients":{"0":{"name":"Background Colour Liquid","displayColor":"#bbbbbb","description":"Water that will be used to form the background of the pixel art","serialize":false,"liquidGroupId":"0"},"1":{"name":"Robin Red Colour","displayColor":"#ff4f4f","description":"Water used for the red of a robin","serialize":false,"liquidGroupId":"1"},"2":{"name":"Robin Brown Colour","displayColor":"#b5651d","description":"Brown Colour of the robin","serialize":false,"liquidGroupId":"2"},"3":{"name":"Robin Black Colour","displayColor":"#2d2d2d","description":"Black colour for robin","serialize":false,"liquidGroupId":"3"}},"ingredLocations":{"09eaa8f8-7a48-4486-8014-6cccc0f389a1:opentrons/nest_12_reservoir_15ml/1":{"A1":{"0":{"volume":10000}},"A2":{"1":{"volume":10000}},"A3":{"2":{"volume":10000}},"A4":{"3":{"volume":10000}}}},"savedStepForms":{"__INITIAL_DECK_SETUP_STEP__":{"stepType":"manualIntervention","id":"__INITIAL_DECK_SETUP_STEP__","labwareLocationUpdate":{"42b25c46-8c44-41dc-b7cf-26ed62c1f64e:opentrons/opentrons_96_tiprack_1000ul/1":"4","09eaa8f8-7a48-4486-8014-6cccc0f389a1:opentrons/nest_12_reservoir_15ml/1":"5","85382d11-cf10-4933-8dae-bd69bbdd1edc:opentrons/nest_96_wellplate_100ul_pcr_full_skirt/2":"2"},"pipetteLocationUpdate":{"44539684-2a7a-4443-b90c-9886bb3b0e05":"right"},"moduleLocationUpdate":{}},"0f05f102-f502-4785-bea1-6361766c2073":{"id":"0f05f102-f502-4785-bea1-6361766c2073","stepType":"moveLiquid","stepName":"transfer","stepDetails":"","pipette":"44539684-2a7a-4443-b90c-9886bb3b0e05","volume":"75","tipRack":"opentrons/opentrons_96_tiprack_1000ul/1","changeTip":"once","path":"multiDispense","aspirate_wells_grouped":false,"aspirate_flowRate":null,"aspirate_labware":"09eaa8f8-7a48-4486-8014-6cccc0f389a1:opentrons/nest_12_reservoir_15ml/1","aspirate_wells":["A2"],"aspirate_wellOrder_first":"t2b","aspirate_wellOrder_second":"l2r","aspirate_mix_checkbox":false,"aspirate_mix_times":null,"aspirate_mix_volume":null,"aspirate_mmFromBottom":null,"aspirate_touchTip_checkbox":false,"aspirate_touchTip_mmFromBottom":null,"dispense_flowRate":null,"dispense_labware":"85382d11-cf10-4933-8dae-bd69bbdd1edc:opentrons/nest_96_wellplate_100ul_pcr_full_skirt/2","dispense_wells":["D3","B4","C4","D4","E4","C5","D5","E5","C6","D6","E6","D7","E7"],"dispense_wellOrder_first":"t2b","dispense_wellOrder_second":"l2r","dispense_mix_checkbox":false,"dispense_mix_times":null,"dispense_mix_volume":null,"dispense_mmFromBottom":null,"dispense_touchTip_checkbox":false,"dispense_touchTip_mmFromBottom":null,"disposalVolume_checkbox":false,"disposalVolume_volume":null,"blowout_checkbox":false,"blowout_location":null,"preWetTip":false,"aspirate_airGap_checkbox":false,"aspirate_airGap_volume":"100","aspirate_delay_checkbox":false,"aspirate_delay_mmFromBottom":null,"aspirate_delay_seconds":"1","dispense_airGap_checkbox":false,"dispense_airGap_volume":"100","dispense_delay_checkbox":false,"dispense_delay_seconds":"1","dispense_delay_mmFromBottom":null,"dropTip_location":"c0775c3c-ae26-48bf-9763-048c336eed90:trashBin","nozzles":null,"dispense_x_position":0,"dispense_y_position":0,"aspirate_x_position":0,"aspirate_y_position":0,"blowout_z_offset":0,"blowout_flowRate":null},"2bf67395-27e9-4c66-8ec4-460201adc6ee":{"id":"2bf67395-27e9-4c66-8ec4-460201adc6ee","stepType":"moveLiquid","stepName":"transfer","stepDetails":"","pipette":"44539684-2a7a-4443-b90c-9886bb3b0e05","volume":"75","tipRack":"opentrons/opentrons_96_tiprack_1000ul/1","changeTip":"once","path":"multiDispense","aspirate_wells_grouped":false,"aspirate_flowRate":null,"aspirate_labware":"09eaa8f8-7a48-4486-8014-6cccc0f389a1:opentrons/nest_12_reservoir_15ml/1","aspirate_wells":["A3"],"aspirate_wellOrder_first":"t2b","aspirate_wellOrder_second":"l2r","aspirate_mix_checkbox":false,"aspirate_mix_times":null,"aspirate_mix_volume":null,"aspirate_mmFromBottom":null,"aspirate_touchTip_checkbox":false,"aspirate_touchTip_mmFromBottom":null,"dispense_flowRate":null,"dispense_labware":"85382d11-cf10-4933-8dae-bd69bbdd1edc:opentrons/nest_96_wellplate_100ul_pcr_full_skirt/2","dispense_wells":["A4","A5","A6","B6","A7","B7","C7","B8","C8","D8","C9","D9","E9","F9","E10","F10","G10","F11","G11"],"dispense_wellOrder_first":"t2b","dispense_wellOrder_second":"l2r","dispense_mix_checkbox":false,"dispense_mix_times":null,"dispense_mix_volume":null,"dispense_mmFromBottom":null,"dispense_touchTip_checkbox":false,"dispense_touchTip_mmFromBottom":null,"disposalVolume_checkbox":false,"disposalVolume_volume":null,"blowout_checkbox":false,"blowout_location":null,"preWetTip":false,"aspirate_airGap_checkbox":false,"aspirate_airGap_volume":"100","aspirate_delay_checkbox":false,"aspirate_delay_mmFromBottom":null,"aspirate_delay_seconds":"1","dispense_airGap_checkbox":false,"dispense_airGap_volume":"100","dispense_delay_checkbox":false,"dispense_delay_seconds":"1","dispense_delay_mmFromBottom":null,"dropTip_location":"c0775c3c-ae26-48bf-9763-048c336eed90:trashBin","nozzles":null,"dispense_x_position":0,"dispense_y_position":0,"aspirate_x_position":0,"aspirate_y_position":0,"blowout_z_offset":0,"blowout_flowRate":null},"78ef7f83-837f-4624-91d9-c2fe87deb6c8":{"id":"78ef7f83-837f-4624-91d9-c2fe87deb6c8","stepType":"moveLiquid","stepName":"transfer","stepDetails":"","pipette":"44539684-2a7a-4443-b90c-9886bb3b0e05","volume":"75","tipRack":"opentrons/opentrons_96_tiprack_1000ul/1","changeTip":"always","path":"single","aspirate_wells_grouped":false,"aspirate_flowRate":null,"aspirate_labware":"09eaa8f8-7a48-4486-8014-6cccc0f389a1:opentrons/nest_12_reservoir_15ml/1","aspirate_wells":["A1"],"aspirate_wellOrder_first":"t2b","aspirate_wellOrder_second":"l2r","aspirate_mix_checkbox":false,"aspirate_mix_times":null,"aspirate_mix_volume":null,"aspirate_mmFromBottom":null,"aspirate_touchTip_checkbox":false,"aspirate_touchTip_mmFromBottom":null,"dispense_flowRate":null,"dispense_labware":"85382d11-cf10-4933-8dae-bd69bbdd1edc:opentrons/nest_96_wellplate_100ul_pcr_full_skirt/2","dispense_wells":["E3","F4","G4","F5","F6","G6","F7","E8","F8","G8"],"dispense_wellOrder_first":"t2b","dispense_wellOrder_second":"l2r","dispense_mix_checkbox":false,"dispense_mix_times":null,"dispense_mix_volume":null,"dispense_mmFromBottom":null,"dispense_touchTip_checkbox":false,"dispense_touchTip_mmFromBottom":null,"disposalVolume_checkbox":true,"disposalVolume_volume":"100","blowout_checkbox":false,"blowout_location":null,"preWetTip":false,"aspirate_airGap_checkbox":false,"aspirate_airGap_volume":"100","aspirate_delay_checkbox":false,"aspirate_delay_mmFromBottom":null,"aspirate_delay_seconds":"1","dispense_airGap_checkbox":false,"dispense_airGap_volume":"100","dispense_delay_checkbox":false,"dispense_delay_seconds":"1","dispense_delay_mmFromBottom":null,"dropTip_location":"c0775c3c-ae26-48bf-9763-048c336eed90:trashBin","nozzles":null,"dispense_x_position":0,"dispense_y_position":0,"aspirate_x_position":0,"aspirate_y_position":0,"blowout_z_offset":0,"blowout_flowRate":null},"c90a7fa3-d866-425e-a0da-920b2c416493":{"id":"c90a7fa3-d866-425e-a0da-920b2c416493","stepType":"moveLiquid","stepName":"transfer","stepDetails":"","pipette":"44539684-2a7a-4443-b90c-9886bb3b0e05","volume":"75","tipRack":"opentrons/opentrons_96_tiprack_1000ul/1","changeTip":"once","path":"multiDispense","aspirate_wells_grouped":false,"aspirate_flowRate":null,"aspirate_labware":"09eaa8f8-7a48-4486-8014-6cccc0f389a1:opentrons/nest_12_reservoir_15ml/1","aspirate_wells":["A4"],"aspirate_wellOrder_first":"t2b","aspirate_wellOrder_second":"l2r","aspirate_mix_checkbox":false,"aspirate_mix_times":null,"aspirate_mix_volume":null,"aspirate_mmFromBottom":null,"aspirate_touchTip_checkbox":false,"aspirate_touchTip_mmFromBottom":null,"dispense_flowRate":null,"dispense_labware":"85382d11-cf10-4933-8dae-bd69bbdd1edc:opentrons/nest_96_wellplate_100ul_pcr_full_skirt/2","dispense_wells":["H4","B5","G5","G7","H8"],"dispense_wellOrder_first":"t2b","dispense_wellOrder_second":"l2r","dispense_mix_checkbox":false,"dispense_mix_times":null,"dispense_mix_volume":null,"dispense_mmFromBottom":null,"dispense_touchTip_checkbox":false,"dispense_touchTip_mmFromBottom":null,"disposalVolume_checkbox":false,"disposalVolume_volume":null,"blowout_checkbox":false,"blowout_location":null,"preWetTip":false,"aspirate_airGap_checkbox":false,"aspirate_airGap_volume":"100","aspirate_delay_checkbox":false,"aspirate_delay_mmFromBottom":null,"aspirate_delay_seconds":"1","dispense_airGap_checkbox":false,"dispense_airGap_volume":"100","dispense_delay_checkbox":false,"dispense_delay_seconds":"1","dispense_delay_mmFromBottom":null,"dropTip_location":"c0775c3c-ae26-48bf-9763-048c336eed90:trashBin","nozzles":null,"dispense_x_position":0,"dispense_y_position":0,"aspirate_x_position":0,"aspirate_y_position":0,"blowout_z_offset":0,"blowout_flowRate":null}},"orderedStepIds":["0f05f102-f502-4785-bea1-6361766c2073","2bf67395-27e9-4c66-8ec4-460201adc6ee","78ef7f83-837f-4624-91d9-c2fe87deb6c8","c90a7fa3-d866-425e-a0da-920b2c416493"]}},"robot":{"model":"OT-2 Standard","deckId":"ot2_standard"},"labwareDefinitionSchemaId":"opentronsLabwareSchemaV2","labwareDefinitions":{"opentrons/opentrons_96_tiprack_1000ul/1":{"ordering":[["A1","B1","C1","D1","E1","F1","G1","H1"],["A2","B2","C2","D2","E2","F2","G2","H2"],["A3","B3","C3","D3","E3","F3","G3","H3"],["A4","B4","C4","D4","E4","F4","G4","H4"],["A5","B5","C5","D5","E5","F5","G5","H5"],["A6","B6","C6","D6","E6","F6","G6","H6"],["A7","B7","C7","D7","E7","F7","G7","H7"],["A8","B8","C8","D8","E8","F8","G8","H8"],["A9","B9","C9","D9","E9","F9","G9","H9"],["A10","B10","C10","D10","E10","F10","G10","H10"],["A11","B11","C11","D11","E11","F11","G11","H11"],["A12","B12","C12","D12","E12","F12","G12","H12"]],"brand":{"brand":"Opentrons","brandId":[],"links":["https://shop.opentrons.com/collections/opentrons-tips/products/opentrons-1000ul-tips"]},"metadata":{"displayName":"Opentrons OT-2 96 Tip Rack 1000 µL","displayCategory":"tipRack","displayVolumeUnits":"µL","tags":[]},"dimensions":{"xDimension":127.76,"yDimension":85.48,"zDimension":97.47},"wells":{"A1":{"depth":88,"shape":"circular","diameter":7.23,"totalLiquidVolume":1000,"x":14.38,"y":74.24,"z":9.47},"B1":{"depth":88,"shape":"circular","diameter":7.23,"totalLiquidVolume":1000,"x":14.38,"y":65.24,"z":9.47},"C1":{"depth":88,"shape":"circular","diameter":7.23,"totalLiquidVolume":1000,"x":14.38,"y":56.24,"z":9.47},"D1":{"depth":88,"shape":"circular","diameter":7.23,"totalLiquidVolume":1000,"x":14.38,"y":47.24,"z":9.47},"E1":{"depth":88,"shape":"circular","diameter":7.23,"totalLiquidVolume":1000,"x":14.38,"y":38.24,"z":9.47},"F1":{"depth":88,"shape":"circular","diameter":7.23,"totalLiquidVolume":1000,"x":14.38,"y":29.24,"z":9.47},"G1":{"depth":88,"shape":"circular","diameter":7.23,"totalLiquidVolume":1000,"x":14.38,"y":20.24,"z":9.47},"H1":{"depth":88,"shape":"circular","diameter":7.23,"totalLiquidVolume":1000,"x":14.38,"y":11.24,"z":9.47},"A2":{"depth":88,"shape":"circular","diameter":7.23,"totalLiquidVolume":1000,"x":23.38,"y":74.24,"z":9.47},"B2":{"depth":88,"shape":"circular","diameter":7.23,"totalLiquidVolume":1000,"x":23.38,"y":65.24,"z":9.47},"C2":{"depth":88,"shape":"circular","diameter":7.23,"totalLiquidVolume":1000,"x":23.38,"y":56.24,"z":9.47},"D2":{"depth":88,"shape":"circular","diameter":7.23,"totalLiquidVolume":1000,"x":23.38,"y":47.24,"z":9.47},"E2":{"depth":88,"shape":"circular","diameter":7.23,"totalLiquidVolume":1000,"x":23.38,"y":38.24,"z":9.47},"F2":{"depth":88,"shape":"circular","diameter":7.23,"totalLiquidVolume":1000,"x":23.38,"y":29.24,"z":9.47},"G2":{"depth":88,"shape":"circular","diameter":7.23,"totalLiquidVolume":1000,"x":23.38,"y":20.24,"z":9.47},"H2":{"depth":88,"shape":"circular","diameter":7.23,"totalLiquidVolume":1000,"x":23.38,"y":11.24,"z":9.47},"A3":{"depth":88,"shape":"circular","diameter":7.23,"totalLiquidVolume":1000,"x":32.38,"y":74.24,"z":9.47},"B3":{"depth":88,"shape":"circular","diameter":7.23,"totalLiquidVolume":1000,"x":32.38,"y":65.24,"z":9.47},"C3":{"depth":88,"shape":"circular","diameter":7.23,"totalLiquidVolume":1000,"x":32.38,"y":56.24,"z":9.47},"D3":{"depth":88,"shape":"circular","diameter":7.23,"totalLiquidVolume":1000,"x":32.38,"y":47.24,"z":9.47},"E3":{"depth":88,"shape":"circular","diameter":7.23,"totalLiquidVolume":1000,"x":32.38,"y":38.24,"z":9.47},"F3":{"depth":88,"shape":"circular","diameter":7.23,"totalLiquidVolume":1000,"x":32.38,"y":29.24,"z":9.47},"G3":{"depth":88,"shape":"circular","diameter":7.23,"totalLiquidVolume":1000,"x":32.38,"y":20.24,"z":9.47},"H3":{"depth":88,"shape":"circular","diameter":7.23,"totalLiquidVolume":1000,"x":32.38,"y":11.24,"z":9.47},"A4":{"depth":88,"shape":"circular","diameter":7.23,"totalLiquidVolume":1000,"x":41.38,"y":74.24,"z":9.47},"B4":{"depth":88,"shape":"circular","diameter":7.23,"totalLiquidVolume":1000,"x":41.38,"y":65.24,"z":9.47},"C4":{"depth":88,"shape":"circular","diameter":7.23,"totalLiquidVolume":1000,"x":41.38,"y":56.24,"z":9.47},"D4":{"depth":88,"shape":"circular","diameter":7.23,"totalLiquidVolume":1000,"x":41.38,"y":47.24,"z":9.47},"E4":{"depth":88,"shape":"circular","diameter":7.23,"totalLiquidVolume":1000,"x":41.38,"y":38.24,"z":9.47},"F4":{"depth":88,"shape":"circular","diameter":7.23,"totalLiquidVolume":1000,"x":41.38,"y":29.24,"z":9.47},"G4":{"depth":88,"shape":"circular","diameter":7.23,"totalLiquidVolume":1000,"x":41.38,"y":20.24,"z":9.47},"H4":{"depth":88,"shape":"circular","diameter":7.23,"totalLiquidVolume":1000,"x":41.38,"y":11.24,"z":9.47},"A5":{"depth":88,"shape":"circular","diameter":7.23,"totalLiquidVolume":1000,"x":50.38,"y":74.24,"z":9.47},"B5":{"depth":88,"shape":"circular","diameter":7.23,"totalLiquidVolume":1000,"x":50.38,"y":65.24,"z":9.47},"C5":{"depth":88,"shape":"circular","diameter":7.23,"totalLiquidVolume":1000,"x":50.38,"y":56.24,"z":9.47},"D5":{"depth":88,"shape":"circular","diameter":7.23,"totalLiquidVolume":1000,"x":50.38,"y":47.24,"z":9.47},"E5":{"depth":88,"shape":"circular","diameter":7.23,"totalLiquidVolume":1000,"x":50.38,"y":38.24,"z":9.47},"F5":{"depth":88,"shape":"circular","diameter":7.23,"totalLiquidVolume":1000,"x":50.38,"y":29.24,"z":9.47},"G5":{"depth":88,"shape":"circular","diameter":7.23,"totalLiquidVolume":1000,"x":50.38,"y":20.24,"z":9.47},"H5":{"depth":88,"shape":"circular","diameter":7.23,"totalLiquidVolume":1000,"x":50.38,"y":11.24,"z":9.47},"A6":{"depth":88,"shape":"circular","diameter":7.23,"totalLiquidVolume":1000,"x":59.38,"y":74.24,"z":9.47},"B6":{"depth":88,"shape":"circular","diameter":7.23,"totalLiquidVolume":1000,"x":59.38,"y":65.24,"z":9.47},"C6":{"depth":88,"shape":"circular","diameter":7.23,"totalLiquidVolume":1000,"x":59.38,"y":56.24,"z":9.47},"D6":{"depth":88,"shape":"circular","diameter":7.23,"totalLiquidVolume":1000,"x":59.38,"y":47.24,"z":9.47},"E6":{"depth":88,"shape":"circular","diameter":7.23,"totalLiquidVolume":1000,"x":59.38,"y":38.24,"z":9.47},"F6":{"depth":88,"shape":"circular","diameter":7.23,"totalLiquidVolume":1000,"x":59.38,"y":29.24,"z":9.47},"G6":{"depth":88,"shape":"circular","diameter":7.23,"totalLiquidVolume":1000,"x":59.38,"y":20.24,"z":9.47},"H6":{"depth":88,"shape":"circular","diameter":7.23,"totalLiquidVolume":1000,"x":59.38,"y":11.24,"z":9.47},"A7":{"depth":88,"shape":"circular","diameter":7.23,"totalLiquidVolume":1000,"x":68.38,"y":74.24,"z":9.47},"B7":{"depth":88,"shape":"circular","diameter":7.23,"totalLiquidVolume":1000,"x":68.38,"y":65.24,"z":9.47},"C7":{"depth":88,"shape":"circular","diameter":7.23,"totalLiquidVolume":1000,"x":68.38,"y":56.24,"z":9.47},"D7":{"depth":88,"shape":"circular","diameter":7.23,"totalLiquidVolume":1000,"x":68.38,"y":47.24,"z":9.47},"E7":{"depth":88,"shape":"circular","diameter":7.23,"totalLiquidVolume":1000,"x":68.38,"y":38.24,"z":9.47},"F7":{"depth":88,"shape":"circular","diameter":7.23,"totalLiquidVolume":1000,"x":68.38,"y":29.24,"z":9.47},"G7":{"depth":88,"shape":"circular","diameter":7.23,"totalLiquidVolume":1000,"x":68.38,"y":20.24,"z":9.47},"H7":{"depth":88,"shape":"circular","diameter":7.23,"totalLiquidVolume":1000,"x":68.38,"y":11.24,"z":9.47},"A8":{"depth":88,"shape":"circular","diameter":7.23,"totalLiquidVolume":1000,"x":77.38,"y":74.24,"z":9.47},"B8":{"depth":88,"shape":"circular","diameter":7.23,"totalLiquidVolume":1000,"x":77.38,"y":65.24,"z":9.47},"C8":{"depth":88,"shape":"circular","diameter":7.23,"totalLiquidVolume":1000,"x":77.38,"y":56.24,"z":9.47},"D8":{"depth":88,"shape":"circular","diameter":7.23,"totalLiquidVolume":1000,"x":77.38,"y":47.24,"z":9.47},"E8":{"depth":88,"shape":"circular","diameter":7.23,"totalLiquidVolume":1000,"x":77.38,"y":38.24,"z":9.47},"F8":{"depth":88,"shape":"circular","diameter":7.23,"totalLiquidVolume":1000,"x":77.38,"y":29.24,"z":9.47},"G8":{"depth":88,"shape":"circular","diameter":7.23,"totalLiquidVolume":1000,"x":77.38,"y":20.24,"z":9.47},"H8":{"depth":88,"shape":"circular","diameter":7.23,"totalLiquidVolume":1000,"x":77.38,"y":11.24,"z":9.47},"A9":{"depth":88,"shape":"circular","diameter":7.23,"totalLiquidVolume":1000,"x":86.38,"y":74.24,"z":9.47},"B9":{"depth":88,"shape":"circular","diameter":7.23,"totalLiquidVolume":1000,"x":86.38,"y":65.24,"z":9.47},"C9":{"depth":88,"shape":"circular","diameter":7.23,"totalLiquidVolume":1000,"x":86.38,"y":56.24,"z":9.47},"D9":{"depth":88,"shape":"circular","diameter":7.23,"totalLiquidVolume":1000,"x":86.38,"y":47.24,"z":9.47},"E9":{"depth":88,"shape":"circular","diameter":7.23,"totalLiquidVolume":1000,"x":86.38,"y":38.24,"z":9.47},"F9":{"depth":88,"shape":"circular","diameter":7.23,"totalLiquidVolume":1000,"x":86.38,"y":29.24,"z":9.47},"G9":{"depth":88,"shape":"circular","diameter":7.23,"totalLiquidVolume":1000,"x":86.38,"y":20.24,"z":9.47},"H9":{"depth":88,"shape":"circular","diameter":7.23,"totalLiquidVolume":1000,"x":86.38,"y":11.24,"z":9.47},"A10":{"depth":88,"shape":"circular","diameter":7.23,"totalLiquidVolume":1000,"x":95.38,"y":74.24,"z":9.47},"B10":{"depth":88,"shape":"circular","diameter":7.23,"totalLiquidVolume":1000,"x":95.38,"y":65.24,"z":9.47},"C10":{"depth":88,"shape":"circular","diameter":7.23,"totalLiquidVolume":1000,"x":95.38,"y":56.24,"z":9.47},"D10":{"depth":88,"shape":"circular","diameter":7.23,"totalLiquidVolume":1000,"x":95.38,"y":47.24,"z":9.47},"E10":{"depth":88,"shape":"circular","diameter":7.23,"totalLiquidVolume":1000,"x":95.38,"y":38.24,"z":9.47},"F10":{"depth":88,"shape":"circular","diameter":7.23,"totalLiquidVolume":1000,"x":95.38,"y":29.24,"z":9.47},"G10":{"depth":88,"shape":"circular","diameter":7.23,"totalLiquidVolume":1000,"x":95.38,"y":20.24,"z":9.47},"H10":{"depth":88,"shape":"circular","diameter":7.23,"totalLiquidVolume":1000,"x":95.38,"y":11.24,"z":9.47},"A11":{"depth":88,"shape":"circular","diameter":7.23,"totalLiquidVolume":1000,"x":104.38,"y":74.24,"z":9.47},"B11":{"depth":88,"shape":"circular","diameter":7.23,"totalLiquidVolume":1000,"x":104.38,"y":65.24,"z":9.47},"C11":{"depth":88,"shape":"circular","diameter":7.23,"totalLiquidVolume":1000,"x":104.38,"y":56.24,"z":9.47},"D11":{"depth":88,"shape":"circular","diameter":7.23,"totalLiquidVolume":1000,"x":104.38,"y":47.24,"z":9.47},"E11":{"depth":88,"shape":"circular","diameter":7.23,"totalLiquidVolume":1000,"x":104.38,"y":38.24,"z":9.47},"F11":{"depth":88,"shape":"circular","diameter":7.23,"totalLiquidVolume":1000,"x":104.38,"y":29.24,"z":9.47},"G11":{"depth":88,"shape":"circular","diameter":7.23,"totalLiquidVolume":1000,"x":104.38,"y":20.24,"z":9.47},"H11":{"depth":88,"shape":"circular","diameter":7.23,"totalLiquidVolume":1000,"x":104.38,"y":11.24,"z":9.47},"A12":{"depth":88,"shape":"circular","diameter":7.23,"totalLiquidVolume":1000,"x":113.38,"y":74.24,"z":9.47},"B12":{"depth":88,"shape":"circular","diameter":7.23,"totalLiquidVolume":1000,"x":113.38,"y":65.24,"z":9.47},"C12":{"depth":88,"shape":"circular","diameter":7.23,"totalLiquidVolume":1000,"x":113.38,"y":56.24,"z":9.47},"D12":{"depth":88,"shape":"circular","diameter":7.23,"totalLiquidVolume":1000,"x":113.38,"y":47.24,"z":9.47},"E12":{"depth":88,"shape":"circular","diameter":7.23,"totalLiquidVolume":1000,"x":113.38,"y":38.24,"z":9.47},"F12":{"depth":88,"shape":"circular","diameter":7.23,"totalLiquidVolume":1000,"x":113.38,"y":29.24,"z":9.47},"G12":{"depth":88,"shape":"circular","diameter":7.23,"totalLiquidVolume":1000,"x":113.38,"y":20.24,"z":9.47},"H12":{"depth":88,"shape":"circular","diameter":7.23,"totalLiquidVolume":1000,"x":113.38,"y":11.24,"z":9.47}},"groups":[{"metadata":{},"wells":["A1","B1","C1","D1","E1","F1","G1","H1","A2","B2","C2","D2","E2","F2","G2","H2","A3","B3","C3","D3","E3","F3","G3","H3","A4","B4","C4","D4","E4","F4","G4","H4","A5","B5","C5","D5","E5","F5","G5","H5","A6","B6","C6","D6","E6","F6","G6","H6","A7","B7","C7","D7","E7","F7","G7","H7","A8","B8","C8","D8","E8","F8","G8","H8","A9","B9","C9","D9","E9","F9","G9","H9","A10","B10","C10","D10","E10","F10","G10","H10","A11","B11","C11","D11","E11","F11","G11","H11","A12","B12","C12","D12","E12","F12","G12","H12"]}],"parameters":{"format":"96Standard","isTiprack":true,"tipLength":88,"tipOverlap":7.95,"isMagneticModuleCompatible":false,"loadName":"opentrons_96_tiprack_1000ul"},"namespace":"opentrons","version":1,"schemaVersion":2,"cornerOffsetFromSlot":{"x":0,"y":0,"z":0}},"opentrons/nest_12_reservoir_15ml/1":{"ordering":[["A1"],["A2"],["A3"],["A4"],["A5"],["A6"],["A7"],["A8"],["A9"],["A10"],["A11"],["A12"]],"brand":{"brand":"NEST","brandId":["360102"],"links":["https://www.nest-biotech.com/reagent-reserviors/59178414.html"]},"metadata":{"displayName":"NEST 12 Well Reservoir 15 mL","displayCategory":"reservoir","displayVolumeUnits":"mL","tags":[]},"dimensions":{"xDimension":127.76,"yDimension":85.48,"zDimension":31.4},"wells":{"A1":{"depth":26.85,"shape":"rectangular","xDimension":8.2,"yDimension":71.2,"totalLiquidVolume":15000,"x":14.38,"y":42.78,"z":4.55},"A2":{"depth":26.85,"shape":"rectangular","xDimension":8.2,"yDimension":71.2,"totalLiquidVolume":15000,"x":23.38,"y":42.78,"z":4.55},"A3":{"depth":26.85,"shape":"rectangular","xDimension":8.2,"yDimension":71.2,"totalLiquidVolume":15000,"x":32.38,"y":42.78,"z":4.55},"A4":{"depth":26.85,"shape":"rectangular","xDimension":8.2,"yDimension":71.2,"totalLiquidVolume":15000,"x":41.38,"y":42.78,"z":4.55},"A5":{"depth":26.85,"shape":"rectangular","xDimension":8.2,"yDimension":71.2,"totalLiquidVolume":15000,"x":50.38,"y":42.78,"z":4.55},"A6":{"depth":26.85,"shape":"rectangular","xDimension":8.2,"yDimension":71.2,"totalLiquidVolume":15000,"x":59.38,"y":42.78,"z":4.55},"A7":{"depth":26.85,"shape":"rectangular","xDimension":8.2,"yDimension":71.2,"totalLiquidVolume":15000,"x":68.38,"y":42.78,"z":4.55},"A8":{"depth":26.85,"shape":"rectangular","xDimension":8.2,"yDimension":71.2,"totalLiquidVolume":15000,"x":77.38,"y":42.78,"z":4.55},"A9":{"depth":26.85,"shape":"rectangular","xDimension":8.2,"yDimension":71.2,"totalLiquidVolume":15000,"x":86.38,"y":42.78,"z":4.55},"A10":{"depth":26.85,"shape":"rectangular","xDimension":8.2,"yDimension":71.2,"totalLiquidVolume":15000,"x":95.38,"y":42.78,"z":4.55},"A11":{"depth":26.85,"shape":"rectangular","xDimension":8.2,"yDimension":71.2,"totalLiquidVolume":15000,"x":104.38,"y":42.78,"z":4.55},"A12":{"depth":26.85,"shape":"rectangular","xDimension":8.2,"yDimension":71.2,"totalLiquidVolume":15000,"x":113.38,"y":42.78,"z":4.55}},"groups":[{"metadata":{"wellBottomShape":"v"},"wells":["A1","A2","A3","A4","A5","A6","A7","A8","A9","A10","A11","A12"]}],"parameters":{"format":"trough","isTiprack":false,"isMagneticModuleCompatible":false,"quirks":["centerMultichannelOnWells","touchTipDisabled"],"loadName":"nest_12_reservoir_15ml"},"namespace":"opentrons","version":1,"schemaVersion":2,"cornerOffsetFromSlot":{"x":0,"y":0,"z":0}},"opentrons/nest_96_wellplate_100ul_pcr_full_skirt/2":{"ordering":[["A1","B1","C1","D1","E1","F1","G1","H1"],["A2","B2","C2","D2","E2","F2","G2","H2"],["A3","B3","C3","D3","E3","F3","G3","H3"],["A4","B4","C4","D4","E4","F4","G4","H4"],["A5","B5","C5","D5","E5","F5","G5","H5"],["A6","B6","C6","D6","E6","F6","G6","H6"],["A7","B7","C7","D7","E7","F7","G7","H7"],["A8","B8","C8","D8","E8","F8","G8","H8"],["A9","B9","C9","D9","E9","F9","G9","H9"],["A10","B10","C10","D10","E10","F10","G10","H10"],["A11","B11","C11","D11","E11","F11","G11","H11"],["A12","B12","C12","D12","E12","F12","G12","H12"]],"brand":{"brand":"NEST","brandId":["402501"],"links":["https://www.nest-biotech.com/pcr-plates/58773587.html"]},"metadata":{"displayName":"NEST 96 Well Plate 100 µL PCR Full Skirt","displayCategory":"wellPlate","displayVolumeUnits":"µL","tags":[]},"dimensions":{"xDimension":127.76,"yDimension":85.48,"zDimension":15.7},"gripForce":15,"gripHeightFromLabwareBottom":10.65,"wells":{"A1":{"depth":14.78,"shape":"circular","diameter":5.34,"totalLiquidVolume":100,"x":14.38,"y":74.24,"z":0.92},"B1":{"depth":14.78,"shape":"circular","diameter":5.34,"totalLiquidVolume":100,"x":14.38,"y":65.24,"z":0.92},"C1":{"depth":14.78,"shape":"circular","diameter":5.34,"totalLiquidVolume":100,"x":14.38,"y":56.24,"z":0.92},"D1":{"depth":14.78,"shape":"circular","diameter":5.34,"totalLiquidVolume":100,"x":14.38,"y":47.24,"z":0.92},"E1":{"depth":14.78,"shape":"circular","diameter":5.34,"totalLiquidVolume":100,"x":14.38,"y":38.24,"z":0.92},"F1":{"depth":14.78,"shape":"circular","diameter":5.34,"totalLiquidVolume":100,"x":14.38,"y":29.24,"z":0.92},"G1":{"depth":14.78,"shape":"circular","diameter":5.34,"totalLiquidVolume":100,"x":14.38,"y":20.24,"z":0.92},"H1":{"depth":14.78,"shape":"circular","diameter":5.34,"totalLiquidVolume":100,"x":14.38,"y":11.24,"z":0.92},"A2":{"depth":14.78,"shape":"circular","diameter":5.34,"totalLiquidVolume":100,"x":23.38,"y":74.24,"z":0.92},"B2":{"depth":14.78,"shape":"circular","diameter":5.34,"totalLiquidVolume":100,"x":23.38,"y":65.24,"z":0.92},"C2":{"depth":14.78,"shape":"circular","diameter":5.34,"totalLiquidVolume":100,"x":23.38,"y":56.24,"z":0.92},"D2":{"depth":14.78,"shape":"circular","diameter":5.34,"totalLiquidVolume":100,"x":23.38,"y":47.24,"z":0.92},"E2":{"depth":14.78,"shape":"circular","diameter":5.34,"totalLiquidVolume":100,"x":23.38,"y":38.24,"z":0.92},"F2":{"depth":14.78,"shape":"circular","diameter":5.34,"totalLiquidVolume":100,"x":23.38,"y":29.24,"z":0.92},"G2":{"depth":14.78,"shape":"circular","diameter":5.34,"totalLiquidVolume":100,"x":23.38,"y":20.24,"z":0.92},"H2":{"depth":14.78,"shape":"circular","diameter":5.34,"totalLiquidVolume":100,"x":23.38,"y":11.24,"z":0.92},"A3":{"depth":14.78,"shape":"circular","diameter":5.34,"totalLiquidVolume":100,"x":32.38,"y":74.24,"z":0.92},"B3":{"depth":14.78,"shape":"circular","diameter":5.34,"totalLiquidVolume":100,"x":32.38,"y":65.24,"z":0.92},"C3":{"depth":14.78,"shape":"circular","diameter":5.34,"totalLiquidVolume":100,"x":32.38,"y":56.24,"z":0.92},"D3":{"depth":14.78,"shape":"circular","diameter":5.34,"totalLiquidVolume":100,"x":32.38,"y":47.24,"z":0.92},"E3":{"depth":14.78,"shape":"circular","diameter":5.34,"totalLiquidVolume":100,"x":32.38,"y":38.24,"z":0.92},"F3":{"depth":14.78,"shape":"circular","diameter":5.34,"totalLiquidVolume":100,"x":32.38,"y":29.24,"z":0.92},"G3":{"depth":14.78,"shape":"circular","diameter":5.34,"totalLiquidVolume":100,"x":32.38,"y":20.24,"z":0.92},"H3":{"depth":14.78,"shape":"circular","diameter":5.34,"totalLiquidVolume":100,"x":32.38,"y":11.24,"z":0.92},"A4":{"depth":14.78,"shape":"circular","diameter":5.34,"totalLiquidVolume":100,"x":41.38,"y":74.24,"z":0.92},"B4":{"depth":14.78,"shape":"circular","diameter":5.34,"totalLiquidVolume":100,"x":41.38,"y":65.24,"z":0.92},"C4":{"depth":14.78,"shape":"circular","diameter":5.34,"totalLiquidVolume":100,"x":41.38,"y":56.24,"z":0.92},"D4":{"depth":14.78,"shape":"circular","diameter":5.34,"totalLiquidVolume":100,"x":41.38,"y":47.24,"z":0.92},"E4":{"depth":14.78,"shape":"circular","diameter":5.34,"totalLiquidVolume":100,"x":41.38,"y":38.24,"z":0.92},"F4":{"depth":14.78,"shape":"circular","diameter":5.34,"totalLiquidVolume":100,"x":41.38,"y":29.24,"z":0.92},"G4":{"depth":14.78,"shape":"circular","diameter":5.34,"totalLiquidVolume":100,"x":41.38,"y":20.24,"z":0.92},"H4":{"depth":14.78,"shape":"circular","diameter":5.34,"totalLiquidVolume":100,"x":41.38,"y":11.24,"z":0.92},"A5":{"depth":14.78,"shape":"circular","diameter":5.34,"totalLiquidVolume":100,"x":50.38,"y":74.24,"z":0.92},"B5":{"depth":14.78,"shape":"circular","diameter":5.34,"totalLiquidVolume":100,"x":50.38,"y":65.24,"z":0.92},"C5":{"depth":14.78,"shape":"circular","diameter":5.34,"totalLiquidVolume":100,"x":50.38,"y":56.24,"z":0.92},"D5":{"depth":14.78,"shape":"circular","diameter":5.34,"totalLiquidVolume":100,"x":50.38,"y":47.24,"z":0.92},"E5":{"depth":14.78,"shape":"circular","diameter":5.34,"totalLiquidVolume":100,"x":50.38,"y":38.24,"z":0.92},"F5":{"depth":14.78,"shape":"circular","diameter":5.34,"totalLiquidVolume":100,"x":50.38,"y":29.24,"z":0.92},"G5":{"depth":14.78,"shape":"circular","diameter":5.34,"totalLiquidVolume":100,"x":50.38,"y":20.24,"z":0.92},"H5":{"depth":14.78,"shape":"circular","diameter":5.34,"totalLiquidVolume":100,"x":50.38,"y":11.24,"z":0.92},"A6":{"depth":14.78,"shape":"circular","diameter":5.34,"totalLiquidVolume":100,"x":59.38,"y":74.24,"z":0.92},"B6":{"depth":14.78,"shape":"circular","diameter":5.34,"totalLiquidVolume":100,"x":59.38,"y":65.24,"z":0.92},"C6":{"depth":14.78,"shape":"circular","diameter":5.34,"totalLiquidVolume":100,"x":59.38,"y":56.24,"z":0.92},"D6":{"depth":14.78,"shape":"circular","diameter":5.34,"totalLiquidVolume":100,"x":59.38,"y":47.24,"z":0.92},"E6":{"depth":14.78,"shape":"circular","diameter":5.34,"totalLiquidVolume":100,"x":59.38,"y":38.24,"z":0.92},"F6":{"depth":14.78,"shape":"circular","diameter":5.34,"totalLiquidVolume":100,"x":59.38,"y":29.24,"z":0.92},"G6":{"depth":14.78,"shape":"circular","diameter":5.34,"totalLiquidVolume":100,"x":59.38,"y":20.24,"z":0.92},"H6":{"depth":14.78,"shape":"circular","diameter":5.34,"totalLiquidVolume":100,"x":59.38,"y":11.24,"z":0.92},"A7":{"depth":14.78,"shape":"circular","diameter":5.34,"totalLiquidVolume":100,"x":68.38,"y":74.24,"z":0.92},"B7":{"depth":14.78,"shape":"circular","diameter":5.34,"totalLiquidVolume":100,"x":68.38,"y":65.24,"z":0.92},"C7":{"depth":14.78,"shape":"circular","diameter":5.34,"totalLiquidVolume":100,"x":68.38,"y":56.24,"z":0.92},"D7":{"depth":14.78,"shape":"circular","diameter":5.34,"totalLiquidVolume":100,"x":68.38,"y":47.24,"z":0.92},"E7":{"depth":14.78,"shape":"circular","diameter":5.34,"totalLiquidVolume":100,"x":68.38,"y":38.24,"z":0.92},"F7":{"depth":14.78,"shape":"circular","diameter":5.34,"totalLiquidVolume":100,"x":68.38,"y":29.24,"z":0.92},"G7":{"depth":14.78,"shape":"circular","diameter":5.34,"totalLiquidVolume":100,"x":68.38,"y":20.24,"z":0.92},"H7":{"depth":14.78,"shape":"circular","diameter":5.34,"totalLiquidVolume":100,"x":68.38,"y":11.24,"z":0.92},"A8":{"depth":14.78,"shape":"circular","diameter":5.34,"totalLiquidVolume":100,"x":77.38,"y":74.24,"z":0.92},"B8":{"depth":14.78,"shape":"circular","diameter":5.34,"totalLiquidVolume":100,"x":77.38,"y":65.24,"z":0.92},"C8":{"depth":14.78,"shape":"circular","diameter":5.34,"totalLiquidVolume":100,"x":77.38,"y":56.24,"z":0.92},"D8":{"depth":14.78,"shape":"circular","diameter":5.34,"totalLiquidVolume":100,"x":77.38,"y":47.24,"z":0.92},"E8":{"depth":14.78,"shape":"circular","diameter":5.34,"totalLiquidVolume":100,"x":77.38,"y":38.24,"z":0.92},"F8":{"depth":14.78,"shape":"circular","diameter":5.34,"totalLiquidVolume":100,"x":77.38,"y":29.24,"z":0.92},"G8":{"depth":14.78,"shape":"circular","diameter":5.34,"totalLiquidVolume":100,"x":77.38,"y":20.24,"z":0.92},"H8":{"depth":14.78,"shape":"circular","diameter":5.34,"totalLiquidVolume":100,"x":77.38,"y":11.24,"z":0.92},"A9":{"depth":14.78,"shape":"circular","diameter":5.34,"totalLiquidVolume":100,"x":86.38,"y":74.24,"z":0.92},"B9":{"depth":14.78,"shape":"circular","diameter":5.34,"totalLiquidVolume":100,"x":86.38,"y":65.24,"z":0.92},"C9":{"depth":14.78,"shape":"circular","diameter":5.34,"totalLiquidVolume":100,"x":86.38,"y":56.24,"z":0.92},"D9":{"depth":14.78,"shape":"circular","diameter":5.34,"totalLiquidVolume":100,"x":86.38,"y":47.24,"z":0.92},"E9":{"depth":14.78,"shape":"circular","diameter":5.34,"totalLiquidVolume":100,"x":86.38,"y":38.24,"z":0.92},"F9":{"depth":14.78,"shape":"circular","diameter":5.34,"totalLiquidVolume":100,"x":86.38,"y":29.24,"z":0.92},"G9":{"depth":14.78,"shape":"circular","diameter":5.34,"totalLiquidVolume":100,"x":86.38,"y":20.24,"z":0.92},"H9":{"depth":14.78,"shape":"circular","diameter":5.34,"totalLiquidVolume":100,"x":86.38,"y":11.24,"z":0.92},"A10":{"depth":14.78,"shape":"circular","diameter":5.34,"totalLiquidVolume":100,"x":95.38,"y":74.24,"z":0.92},"B10":{"depth":14.78,"shape":"circular","diameter":5.34,"totalLiquidVolume":100,"x":95.38,"y":65.24,"z":0.92},"C10":{"depth":14.78,"shape":"circular","diameter":5.34,"totalLiquidVolume":100,"x":95.38,"y":56.24,"z":0.92},"D10":{"depth":14.78,"shape":"circular","diameter":5.34,"totalLiquidVolume":100,"x":95.38,"y":47.24,"z":0.92},"E10":{"depth":14.78,"shape":"circular","diameter":5.34,"totalLiquidVolume":100,"x":95.38,"y":38.24,"z":0.92},"F10":{"depth":14.78,"shape":"circular","diameter":5.34,"totalLiquidVolume":100,"x":95.38,"y":29.24,"z":0.92},"G10":{"depth":14.78,"shape":"circular","diameter":5.34,"totalLiquidVolume":100,"x":95.38,"y":20.24,"z":0.92},"H10":{"depth":14.78,"shape":"circular","diameter":5.34,"totalLiquidVolume":100,"x":95.38,"y":11.24,"z":0.92},"A11":{"depth":14.78,"shape":"circular","diameter":5.34,"totalLiquidVolume":100,"x":104.38,"y":74.24,"z":0.92},"B11":{"depth":14.78,"shape":"circular","diameter":5.34,"totalLiquidVolume":100,"x":104.38,"y":65.24,"z":0.92},"C11":{"depth":14.78,"shape":"circular","diameter":5.34,"totalLiquidVolume":100,"x":104.38,"y":56.24,"z":0.92},"D11":{"depth":14.78,"shape":"circular","diameter":5.34,"totalLiquidVolume":100,"x":104.38,"y":47.24,"z":0.92},"E11":{"depth":14.78,"shape":"circular","diameter":5.34,"totalLiquidVolume":100,"x":104.38,"y":38.24,"z":0.92},"F11":{"depth":14.78,"shape":"circular","diameter":5.34,"totalLiquidVolume":100,"x":104.38,"y":29.24,"z":0.92},"G11":{"depth":14.78,"shape":"circular","diameter":5.34,"totalLiquidVolume":100,"x":104.38,"y":20.24,"z":0.92},"H11":{"depth":14.78,"shape":"circular","diameter":5.34,"totalLiquidVolume":100,"x":104.38,"y":11.24,"z":0.92},"A12":{"depth":14.78,"shape":"circular","diameter":5.34,"totalLiquidVolume":100,"x":113.38,"y":74.24,"z":0.92},"B12":{"depth":14.78,"shape":"circular","diameter":5.34,"totalLiquidVolume":100,"x":113.38,"y":65.24,"z":0.92},"C12":{"depth":14.78,"shape":"circular","diameter":5.34,"totalLiquidVolume":100,"x":113.38,"y":56.24,"z":0.92},"D12":{"depth":14.78,"shape":"circular","diameter":5.34,"totalLiquidVolume":100,"x":113.38,"y":47.24,"z":0.92},"E12":{"depth":14.78,"shape":"circular","diameter":5.34,"totalLiquidVolume":100,"x":113.38,"y":38.24,"z":0.92},"F12":{"depth":14.78,"shape":"circular","diameter":5.34,"totalLiquidVolume":100,"x":113.38,"y":29.24,"z":0.92},"G12":{"depth":14.78,"shape":"circular","diameter":5.34,"totalLiquidVolume":100,"x":113.38,"y":20.24,"z":0.92},"H12":{"depth":14.78,"shape":"circular","diameter":5.34,"totalLiquidVolume":100,"x":113.38,"y":11.24,"z":0.92}},"groups":[{"metadata":{"wellBottomShape":"v"},"wells":["A1","B1","C1","D1","E1","F1","G1","H1","A2","B2","C2","D2","E2","F2","G2","H2","A3","B3","C3","D3","E3","F3","G3","H3","A4","B4","C4","D4","E4","F4","G4","H4","A5","B5","C5","D5","E5","F5","G5","H5","A6","B6","C6","D6","E6","F6","G6","H6","A7","B7","C7","D7","E7","F7","G7","H7","A8","B8","C8","D8","E8","F8","G8","H8","A9","B9","C9","D9","E9","F9","G9","H9","A10","B10","C10","D10","E10","F10","G10","H10","A11","B11","C11","D11","E11","F11","G11","H11","A12","B12","C12","D12","E12","F12","G12","H12"]}],"parameters":{"format":"96Standard","isTiprack":false,"isMagneticModuleCompatible":true,"magneticModuleEngageHeight":20,"loadName":"nest_96_wellplate_100ul_pcr_full_skirt"},"namespace":"opentrons","version":2,"schemaVersion":2,"cornerOffsetFromSlot":{"x":0,"y":0,"z":0},"stackingOffsetWithLabware":{"opentrons_96_pcr_adapter":{"x":0,"y":0,"z":10.2},"opentrons_96_well_aluminum_block":{"x":0,"y":0,"z":12.66}},"stackingOffsetWithModule":{"thermocyclerModuleV2":{"x":0,"y":0,"z":10.8}}}},"liquidSchemaId":"opentronsLiquidSchemaV1","liquids":{"0":{"displayName":"Background Colour Liquid","description":"Water that will be used to form the background of the pixel art","displayColor":"#bbbbbb"},"1":{"displayName":"Robin Red Colour","description":"Water used for the red of a robin","displayColor":"#ff4f4f"},"2":{"displayName":"Robin Brown Colour","description":"Brown Colour of the robin","displayColor":"#b5651d"},"3":{"displayName":"Robin Black Colour","description":"Black colour for robin","displayColor":"#2d2d2d"}},"commandSchemaId":"opentronsCommandSchemaV8","commands":[{"key":"9f43a6ea-3c2d-4b31-8349-e84ee6ea0374","commandType":"loadPipette","params":{"pipetteName":"p1000_single_gen2","mount":"right","pipetteId":"44539684-2a7a-4443-b90c-9886bb3b0e05"}},{"key":"6d7a85e1-b58c-4fe1-8f4e-b4332b320b00","commandType":"loadLabware","params":{"displayName":"Opentrons OT-2 96 Tip Rack 1000 µL","labwareId":"42b25c46-8c44-41dc-b7cf-26ed62c1f64e:opentrons/opentrons_96_tiprack_1000ul/1","loadName":"opentrons_96_tiprack_1000ul","namespace":"opentrons","version":1,"location":{"slotName":"4"}}},{"key":"a7797242-0334-4ea1-9ced-ae1542c8a399","commandType":"loadLabware","params":{"displayName":"NEST 12 Well Reservoir 15 mL","labwareId":"09eaa8f8-7a48-4486-8014-6cccc0f389a1:opentrons/nest_12_reservoir_15ml/1","loadName":"nest_12_reservoir_15ml","namespace":"opentrons","version":1,"location":{"slotName":"5"}}},{"key":"319061f6-ac11-4939-b954-2fba53bc2fc1","commandType":"loadLabware","params":{"displayName":"NEST 96 Well Plate 100 µL PCR Full Skirt","labwareId":"85382d11-cf10-4933-8dae-bd69bbdd1edc:opentrons/nest_96_wellplate_100ul_pcr_full_skirt/2","loadName":"nest_96_wellplate_100ul_pcr_full_skirt","namespace":"opentrons","version":2,"location":{"slotName":"2"}}},{"commandType":"loadLiquid","key":"3e002a5a-b6fb-423d-aa6b-c152ccbb62db","params":{"liquidId":"3","labwareId":"09eaa8f8-7a48-4486-8014-6cccc0f389a1:opentrons/nest_12_reservoir_15ml/1","volumeByWell":{"A4":10000}}},{"commandType":"loadLiquid","key":"83bfeaf0-0bea-4902-9027-860d4ff2f376","params":{"liquidId":"2","labwareId":"09eaa8f8-7a48-4486-8014-6cccc0f389a1:opentrons/nest_12_reservoir_15ml/1","volumeByWell":{"A3":10000}}},{"commandType":"loadLiquid","key":"0701c90f-ed40-4a8f-aa9a-0072938969b9","params":{"liquidId":"1","labwareId":"09eaa8f8-7a48-4486-8014-6cccc0f389a1:opentrons/nest_12_reservoir_15ml/1","volumeByWell":{"A2":10000}}},{"commandType":"loadLiquid","key":"7160e7f2-ddcc-4c7c-b0e5-682c8e092141","params":{"liquidId":"0","labwareId":"09eaa8f8-7a48-4486-8014-6cccc0f389a1:opentrons/nest_12_reservoir_15ml/1","volumeByWell":{"A1":10000}}},{"commandType":"pickUpTip","key":"d618a859-2bb6-4674-b869-9e9388745401","params":{"pipetteId":"44539684-2a7a-4443-b90c-9886bb3b0e05","labwareId":"42b25c46-8c44-41dc-b7cf-26ed62c1f64e:opentrons/opentrons_96_tiprack_1000ul/1","wellName":"A1"}},{"commandType":"aspirate","key":"7d204fe6-bb8f-46fc-a37d-2fb95ae62e30","params":{"pipetteId":"44539684-2a7a-4443-b90c-9886bb3b0e05","volume":975,"labwareId":"09eaa8f8-7a48-4486-8014-6cccc0f389a1:opentrons/nest_12_reservoir_15ml/1","wellName":"A2","wellLocation":{"origin":"bottom","offset":{"z":1,"x":0,"y":0}},"flowRate":274.7}},{"commandType":"dispense","key":"75d50543-1feb-4636-bcb5-0c6f405b8b38","params":{"pipetteId":"44539684-2a7a-4443-b90c-9886bb3b0e05","volume":75,"labwareId":"85382d11-cf10-4933-8dae-bd69bbdd1edc:opentrons/nest_96_wellplate_100ul_pcr_full_skirt/2","wellName":"D3","wellLocation":{"origin":"bottom","offset":{"z":1,"x":0,"y":0}},"flowRate":274.7}},{"commandType":"dispense","key":"fc251655-589e-4226-9041-ccdf54f34405","params":{"pipetteId":"44539684-2a7a-4443-b90c-9886bb3b0e05","volume":75,"labwareId":"85382d11-cf10-4933-8dae-bd69bbdd1edc:opentrons/nest_96_wellplate_100ul_pcr_full_skirt/2","wellName":"B4","wellLocation":{"origin":"bottom","offset":{"z":1,"x":0,"y":0}},"flowRate":274.7}},{"commandType":"dispense","key":"7864d26a-6c15-474e-aaa8-0f9adc7fecd4","params":{"pipetteId":"44539684-2a7a-4443-b90c-9886bb3b0e05","volume":75,"labwareId":"85382d11-cf10-4933-8dae-bd69bbdd1edc:opentrons/nest_96_wellplate_100ul_pcr_full_skirt/2","wellName":"C4","wellLocation":{"origin":"bottom","offset":{"z":1,"x":0,"y":0}},"flowRate":274.7}},{"commandType":"dispense","key":"86696a4a-778c-49f5-a920-9e9d3f0005fc","params":{"pipetteId":"44539684-2a7a-4443-b90c-9886bb3b0e05","volume":75,"labwareId":"85382d11-cf10-4933-8dae-bd69bbdd1edc:opentrons/nest_96_wellplate_100ul_pcr_full_skirt/2","wellName":"D4","wellLocation":{"origin":"bottom","offset":{"z":1,"x":0,"y":0}},"flowRate":274.7}},{"commandType":"dispense","key":"2902db07-f0d5-42e5-97eb-ccdf4a5d4ee3","params":{"pipetteId":"44539684-2a7a-4443-b90c-9886bb3b0e05","volume":75,"labwareId":"85382d11-cf10-4933-8dae-bd69bbdd1edc:opentrons/nest_96_wellplate_100ul_pcr_full_skirt/2","wellName":"E4","wellLocation":{"origin":"bottom","offset":{"z":1,"x":0,"y":0}},"flowRate":274.7}},{"commandType":"dispense","key":"79ee62c3-49f1-4aa1-930b-3b1dc1006218","params":{"pipetteId":"44539684-2a7a-4443-b90c-9886bb3b0e05","volume":75,"labwareId":"85382d11-cf10-4933-8dae-bd69bbdd1edc:opentrons/nest_96_wellplate_100ul_pcr_full_skirt/2","wellName":"C5","wellLocation":{"origin":"bottom","offset":{"z":1,"x":0,"y":0}},"flowRate":274.7}},{"commandType":"dispense","key":"54e22271-a842-4035-98e3-3a9bc02aada4","params":{"pipetteId":"44539684-2a7a-4443-b90c-9886bb3b0e05","volume":75,"labwareId":"85382d11-cf10-4933-8dae-bd69bbdd1edc:opentrons/nest_96_wellplate_100ul_pcr_full_skirt/2","wellName":"D5","wellLocation":{"origin":"bottom","offset":{"z":1,"x":0,"y":0}},"flowRate":274.7}},{"commandType":"dispense","key":"8ed3f4e3-9dda-440f-9864-839ef9915ff0","params":{"pipetteId":"44539684-2a7a-4443-b90c-9886bb3b0e05","volume":75,"labwareId":"85382d11-cf10-4933-8dae-bd69bbdd1edc:opentrons/nest_96_wellplate_100ul_pcr_full_skirt/2","wellName":"E5","wellLocation":{"origin":"bottom","offset":{"z":1,"x":0,"y":0}},"flowRate":274.7}},{"commandType":"dispense","key":"174902f1-8356-43f8-bb72-ad7d18693456","params":{"pipetteId":"44539684-2a7a-4443-b90c-9886bb3b0e05","volume":75,"labwareId":"85382d11-cf10-4933-8dae-bd69bbdd1edc:opentrons/nest_96_wellplate_100ul_pcr_full_skirt/2","wellName":"C6","wellLocation":{"origin":"bottom","offset":{"z":1,"x":0,"y":0}},"flowRate":274.7}},{"commandType":"dispense","key":"ff073075-5163-4c39-a7d3-a7a72c369990","params":{"pipetteId":"44539684-2a7a-4443-b90c-9886bb3b0e05","volume":75,"labwareId":"85382d11-cf10-4933-8dae-bd69bbdd1edc:opentrons/nest_96_wellplate_100ul_pcr_full_skirt/2","wellName":"D6","wellLocation":{"origin":"bottom","offset":{"z":1,"x":0,"y":0}},"flowRate":274.7}},{"commandType":"dispense","key":"7355333f-cd22-4ffe-b698-c0b295eef37b","params":{"pipetteId":"44539684-2a7a-4443-b90c-9886bb3b0e05","volume":75,"labwareId":"85382d11-cf10-4933-8dae-bd69bbdd1edc:opentrons/nest_96_wellplate_100ul_pcr_full_skirt/2","wellName":"E6","wellLocation":{"origin":"bottom","offset":{"z":1,"x":0,"y":0}},"flowRate":274.7}},{"commandType":"dispense","key":"15ae1cb4-9605-4f06-ba19-225f39b10b97","params":{"pipetteId":"44539684-2a7a-4443-b90c-9886bb3b0e05","volume":75,"labwareId":"85382d11-cf10-4933-8dae-bd69bbdd1edc:opentrons/nest_96_wellplate_100ul_pcr_full_skirt/2","wellName":"D7","wellLocation":{"origin":"bottom","offset":{"z":1,"x":0,"y":0}},"flowRate":274.7}},{"commandType":"dispense","key":"65997944-8d0e-4fa3-837c-593e3e21926f","params":{"pipetteId":"44539684-2a7a-4443-b90c-9886bb3b0e05","volume":75,"labwareId":"85382d11-cf10-4933-8dae-bd69bbdd1edc:opentrons/nest_96_wellplate_100ul_pcr_full_skirt/2","wellName":"E7","wellLocation":{"origin":"bottom","offset":{"z":1,"x":0,"y":0}},"flowRate":274.7}},{"commandType":"moveToAddressableAreaForDropTip","key":"6b820991-5bc3-4533-ba88-57088d262538","params":{"pipetteId":"44539684-2a7a-4443-b90c-9886bb3b0e05","addressableAreaName":"fixedTrash","offset":{"x":0,"y":0,"z":0},"alternateDropLocation":true}},{"commandType":"dropTipInPlace","key":"49bcb115-42e3-4efe-998d-41407014da51","params":{"pipetteId":"44539684-2a7a-4443-b90c-9886bb3b0e05"}},{"commandType":"pickUpTip","key":"09af91b3-6688-45b8-b129-1f94cdb7f17e","params":{"pipetteId":"44539684-2a7a-4443-b90c-9886bb3b0e05","labwareId":"42b25c46-8c44-41dc-b7cf-26ed62c1f64e:opentrons/opentrons_96_tiprack_1000ul/1","wellName":"B1"}},{"commandType":"aspirate","key":"2a2ead89-0015-4ed3-ba4c-a80d88d8e256","params":{"pipetteId":"44539684-2a7a-4443-b90c-9886bb3b0e05","volume":975,"labwareId":"09eaa8f8-7a48-4486-8014-6cccc0f389a1:opentrons/nest_12_reservoir_15ml/1","wellName":"A3","wellLocation":{"origin":"bottom","offset":{"z":1,"x":0,"y":0}},"flowRate":274.7}},{"commandType":"dispense","key":"bfc189ca-8a6a-4df5-9e44-ab3c76c82b50","params":{"pipetteId":"44539684-2a7a-4443-b90c-9886bb3b0e05","volume":75,"labwareId":"85382d11-cf10-4933-8dae-bd69bbdd1edc:opentrons/nest_96_wellplate_100ul_pcr_full_skirt/2","wellName":"A4","wellLocation":{"origin":"bottom","offset":{"z":1,"x":0,"y":0}},"flowRate":274.7}},{"commandType":"dispense","key":"80313140-d696-48c2-afd4-eb42469d309a","params":{"pipetteId":"44539684-2a7a-4443-b90c-9886bb3b0e05","volume":75,"labwareId":"85382d11-cf10-4933-8dae-bd69bbdd1edc:opentrons/nest_96_wellplate_100ul_pcr_full_skirt/2","wellName":"A5","wellLocation":{"origin":"bottom","offset":{"z":1,"x":0,"y":0}},"flowRate":274.7}},{"commandType":"dispense","key":"581e7654-027d-44c3-b023-e2d4a15392a6","params":{"pipetteId":"44539684-2a7a-4443-b90c-9886bb3b0e05","volume":75,"labwareId":"85382d11-cf10-4933-8dae-bd69bbdd1edc:opentrons/nest_96_wellplate_100ul_pcr_full_skirt/2","wellName":"A6","wellLocation":{"origin":"bottom","offset":{"z":1,"x":0,"y":0}},"flowRate":274.7}},{"commandType":"dispense","key":"ec01c83a-76ab-415e-88d3-fb42d67f9c5d","params":{"pipetteId":"44539684-2a7a-4443-b90c-9886bb3b0e05","volume":75,"labwareId":"85382d11-cf10-4933-8dae-bd69bbdd1edc:opentrons/nest_96_wellplate_100ul_pcr_full_skirt/2","wellName":"B6","wellLocation":{"origin":"bottom","offset":{"z":1,"x":0,"y":0}},"flowRate":274.7}},{"commandType":"dispense","key":"a84b08ec-1daf-4329-ae8d-299e42d6b2dc","params":{"pipetteId":"44539684-2a7a-4443-b90c-9886bb3b0e05","volume":75,"labwareId":"85382d11-cf10-4933-8dae-bd69bbdd1edc:opentrons/nest_96_wellplate_100ul_pcr_full_skirt/2","wellName":"A7","wellLocation":{"origin":"bottom","offset":{"z":1,"x":0,"y":0}},"flowRate":274.7}},{"commandType":"dispense","key":"9febcd3a-dc29-4e7d-b6ea-4c86c676dd22","params":{"pipetteId":"44539684-2a7a-4443-b90c-9886bb3b0e05","volume":75,"labwareId":"85382d11-cf10-4933-8dae-bd69bbdd1edc:opentrons/nest_96_wellplate_100ul_pcr_full_skirt/2","wellName":"B7","wellLocation":{"origin":"bottom","offset":{"z":1,"x":0,"y":0}},"flowRate":274.7}},{"commandType":"dispense","key":"35ea3adc-6019-4aff-a864-57212c1147c4","params":{"pipetteId":"44539684-2a7a-4443-b90c-9886bb3b0e05","volume":75,"labwareId":"85382d11-cf10-4933-8dae-bd69bbdd1edc:opentrons/nest_96_wellplate_100ul_pcr_full_skirt/2","wellName":"C7","wellLocation":{"origin":"bottom","offset":{"z":1,"x":0,"y":0}},"flowRate":274.7}},{"commandType":"dispense","key":"032f2690-573d-4850-9322-acca6e770bcf","params":{"pipetteId":"44539684-2a7a-4443-b90c-9886bb3b0e05","volume":75,"labwareId":"85382d11-cf10-4933-8dae-bd69bbdd1edc:opentrons/nest_96_wellplate_100ul_pcr_full_skirt/2","wellName":"B8","wellLocation":{"origin":"bottom","offset":{"z":1,"x":0,"y":0}},"flowRate":274.7}},{"commandType":"dispense","key":"c4014f6d-bb20-4494-a07e-3f251cb7196e","params":{"pipetteId":"44539684-2a7a-4443-b90c-9886bb3b0e05","volume":75,"labwareId":"85382d11-cf10-4933-8dae-bd69bbdd1edc:opentrons/nest_96_wellplate_100ul_pcr_full_skirt/2","wellName":"C8","wellLocation":{"origin":"bottom","offset":{"z":1,"x":0,"y":0}},"flowRate":274.7}},{"commandType":"dispense","key":"949e66f8-7e52-4491-a687-27a70ec93306","params":{"pipetteId":"44539684-2a7a-4443-b90c-9886bb3b0e05","volume":75,"labwareId":"85382d11-cf10-4933-8dae-bd69bbdd1edc:opentrons/nest_96_wellplate_100ul_pcr_full_skirt/2","wellName":"D8","wellLocation":{"origin":"bottom","offset":{"z":1,"x":0,"y":0}},"flowRate":274.7}},{"commandType":"dispense","key":"7d00579c-ae12-4b38-94c9-52634c950fc5","params":{"pipetteId":"44539684-2a7a-4443-b90c-9886bb3b0e05","volume":75,"labwareId":"85382d11-cf10-4933-8dae-bd69bbdd1edc:opentrons/nest_96_wellplate_100ul_pcr_full_skirt/2","wellName":"C9","wellLocation":{"origin":"bottom","offset":{"z":1,"x":0,"y":0}},"flowRate":274.7}},{"commandType":"dispense","key":"d5c2989f-eaa6-4c86-ba00-cd03a29f3d44","params":{"pipetteId":"44539684-2a7a-4443-b90c-9886bb3b0e05","volume":75,"labwareId":"85382d11-cf10-4933-8dae-bd69bbdd1edc:opentrons/nest_96_wellplate_100ul_pcr_full_skirt/2","wellName":"D9","wellLocation":{"origin":"bottom","offset":{"z":1,"x":0,"y":0}},"flowRate":274.7}},{"commandType":"dispense","key":"c62bfc7b-4fc2-4fb5-b6a5-8499f7969261","params":{"pipetteId":"44539684-2a7a-4443-b90c-9886bb3b0e05","volume":75,"labwareId":"85382d11-cf10-4933-8dae-bd69bbdd1edc:opentrons/nest_96_wellplate_100ul_pcr_full_skirt/2","wellName":"E9","wellLocation":{"origin":"bottom","offset":{"z":1,"x":0,"y":0}},"flowRate":274.7}},{"commandType":"aspirate","key":"3b82abd6-2bda-4dd7-9297-95d1caec4bea","params":{"pipetteId":"44539684-2a7a-4443-b90c-9886bb3b0e05","volume":450,"labwareId":"09eaa8f8-7a48-4486-8014-6cccc0f389a1:opentrons/nest_12_reservoir_15ml/1","wellName":"A3","wellLocation":{"origin":"bottom","offset":{"z":1,"x":0,"y":0}},"flowRate":274.7}},{"commandType":"dispense","key":"0cf03bed-4738-4234-aea7-83d0a4f0e353","params":{"pipetteId":"44539684-2a7a-4443-b90c-9886bb3b0e05","volume":75,"labwareId":"85382d11-cf10-4933-8dae-bd69bbdd1edc:opentrons/nest_96_wellplate_100ul_pcr_full_skirt/2","wellName":"F9","wellLocation":{"origin":"bottom","offset":{"z":1,"x":0,"y":0}},"flowRate":274.7}},{"commandType":"dispense","key":"1c9e98c6-6c26-4da5-b22c-594bcd1b9b4f","params":{"pipetteId":"44539684-2a7a-4443-b90c-9886bb3b0e05","volume":75,"labwareId":"85382d11-cf10-4933-8dae-bd69bbdd1edc:opentrons/nest_96_wellplate_100ul_pcr_full_skirt/2","wellName":"E10","wellLocation":{"origin":"bottom","offset":{"z":1,"x":0,"y":0}},"flowRate":274.7}},{"commandType":"dispense","key":"860885db-50eb-46f9-98e4-c12f8008fbdd","params":{"pipetteId":"44539684-2a7a-4443-b90c-9886bb3b0e05","volume":75,"labwareId":"85382d11-cf10-4933-8dae-bd69bbdd1edc:opentrons/nest_96_wellplate_100ul_pcr_full_skirt/2","wellName":"F10","wellLocation":{"origin":"bottom","offset":{"z":1,"x":0,"y":0}},"flowRate":274.7}},{"commandType":"dispense","key":"230813f1-88f9-46e7-8e23-0b631b8cc4da","params":{"pipetteId":"44539684-2a7a-4443-b90c-9886bb3b0e05","volume":75,"labwareId":"85382d11-cf10-4933-8dae-bd69bbdd1edc:opentrons/nest_96_wellplate_100ul_pcr_full_skirt/2","wellName":"G10","wellLocation":{"origin":"bottom","offset":{"z":1,"x":0,"y":0}},"flowRate":274.7}},{"commandType":"dispense","key":"89b41980-f823-4890-95c0-1cac5326dc59","params":{"pipetteId":"44539684-2a7a-4443-b90c-9886bb3b0e05","volume":75,"labwareId":"85382d11-cf10-4933-8dae-bd69bbdd1edc:opentrons/nest_96_wellplate_100ul_pcr_full_skirt/2","wellName":"F11","wellLocation":{"origin":"bottom","offset":{"z":1,"x":0,"y":0}},"flowRate":274.7}},{"commandType":"dispense","key":"929e10a2-3024-4ab2-b2fc-381df046904a","params":{"pipetteId":"44539684-2a7a-4443-b90c-9886bb3b0e05","volume":75,"labwareId":"85382d11-cf10-4933-8dae-bd69bbdd1edc:opentrons/nest_96_wellplate_100ul_pcr_full_skirt/2","wellName":"G11","wellLocation":{"origin":"bottom","offset":{"z":1,"x":0,"y":0}},"flowRate":274.7}},{"commandType":"moveToAddressableAreaForDropTip","key":"79198f4c-77ed-4bcc-a413-b0e44d9e98cb","params":{"pipetteId":"44539684-2a7a-4443-b90c-9886bb3b0e05","addressableAreaName":"fixedTrash","offset":{"x":0,"y":0,"z":0},"alternateDropLocation":true}},{"commandType":"dropTipInPlace","key":"3a26cba9-b7e2-4e3b-b820-10467640ddf7","params":{"pipetteId":"44539684-2a7a-4443-b90c-9886bb3b0e05"}},{"commandType":"pickUpTip","key":"51a76a13-f47a-41e8-8a45-4268ce703fda","params":{"pipetteId":"44539684-2a7a-4443-b90c-9886bb3b0e05","labwareId":"42b25c46-8c44-41dc-b7cf-26ed62c1f64e:opentrons/opentrons_96_tiprack_1000ul/1","wellName":"C1"}},{"commandType":"aspirate","key":"73d3d91f-eecc-4366-9d36-818cde671d6d","params":{"pipetteId":"44539684-2a7a-4443-b90c-9886bb3b0e05","volume":75,"labwareId":"09eaa8f8-7a48-4486-8014-6cccc0f389a1:opentrons/nest_12_reservoir_15ml/1","wellName":"A1","wellLocation":{"origin":"bottom","offset":{"z":1,"x":0,"y":0}},"flowRate":274.7}},{"commandType":"dispense","key":"bc8c9602-0524-4d30-b116-5da29253d14a","params":{"pipetteId":"44539684-2a7a-4443-b90c-9886bb3b0e05","volume":75,"labwareId":"85382d11-cf10-4933-8dae-bd69bbdd1edc:opentrons/nest_96_wellplate_100ul_pcr_full_skirt/2","wellName":"E3","wellLocation":{"origin":"bottom","offset":{"z":1,"x":0,"y":0}},"flowRate":274.7}},{"commandType":"moveToAddressableAreaForDropTip","key":"a9a9f136-99e1-4882-9dcb-72452f72996d","params":{"pipetteId":"44539684-2a7a-4443-b90c-9886bb3b0e05","addressableAreaName":"fixedTrash","offset":{"x":0,"y":0,"z":0},"alternateDropLocation":true}},{"commandType":"dropTipInPlace","key":"2371c83c-e6bd-4466-833b-248ddaa64529","params":{"pipetteId":"44539684-2a7a-4443-b90c-9886bb3b0e05"}},{"commandType":"pickUpTip","key":"7f91d401-b7df-49b5-a817-ea5f537c1c3f","params":{"pipetteId":"44539684-2a7a-4443-b90c-9886bb3b0e05","labwareId":"42b25c46-8c44-41dc-b7cf-26ed62c1f64e:opentrons/opentrons_96_tiprack_1000ul/1","wellName":"D1"}},{"commandType":"aspirate","key":"9f9b307f-2dbb-4d7c-9ed3-678d203fa8c3","params":{"pipetteId":"44539684-2a7a-4443-b90c-9886bb3b0e05","volume":75,"labwareId":"09eaa8f8-7a48-4486-8014-6cccc0f389a1:opentrons/nest_12_reservoir_15ml/1","wellName":"A1","wellLocation":{"origin":"bottom","offset":{"z":1,"x":0,"y":0}},"flowRate":274.7}},{"commandType":"dispense","key":"2eb89f70-72c5-4b56-bafc-34ee456e5deb","params":{"pipetteId":"44539684-2a7a-4443-b90c-9886bb3b0e05","volume":75,"labwareId":"85382d11-cf10-4933-8dae-bd69bbdd1edc:opentrons/nest_96_wellplate_100ul_pcr_full_skirt/2","wellName":"F4","wellLocation":{"origin":"bottom","offset":{"z":1,"x":0,"y":0}},"flowRate":274.7}},{"commandType":"moveToAddressableAreaForDropTip","key":"98410491-1a86-4e4e-837c-d37cf1a030ea","params":{"pipetteId":"44539684-2a7a-4443-b90c-9886bb3b0e05","addressableAreaName":"fixedTrash","offset":{"x":0,"y":0,"z":0},"alternateDropLocation":true}},{"commandType":"dropTipInPlace","key":"b2857e59-b98d-4285-8008-e8de3385eac7","params":{"pipetteId":"44539684-2a7a-4443-b90c-9886bb3b0e05"}},{"commandType":"pickUpTip","key":"9465d950-707f-448e-b163-2f1446580bec","params":{"pipetteId":"44539684-2a7a-4443-b90c-9886bb3b0e05","labwareId":"42b25c46-8c44-41dc-b7cf-26ed62c1f64e:opentrons/opentrons_96_tiprack_1000ul/1","wellName":"E1"}},{"commandType":"aspirate","key":"c6968deb-42f9-4c59-aa29-6276d77ea4b6","params":{"pipetteId":"44539684-2a7a-4443-b90c-9886bb3b0e05","volume":75,"labwareId":"09eaa8f8-7a48-4486-8014-6cccc0f389a1:opentrons/nest_12_reservoir_15ml/1","wellName":"A1","wellLocation":{"origin":"bottom","offset":{"z":1,"x":0,"y":0}},"flowRate":274.7}},{"commandType":"dispense","key":"c75f0133-7fc2-4cb2-95a0-32a89d61d311","params":{"pipetteId":"44539684-2a7a-4443-b90c-9886bb3b0e05","volume":75,"labwareId":"85382d11-cf10-4933-8dae-bd69bbdd1edc:opentrons/nest_96_wellplate_100ul_pcr_full_skirt/2","wellName":"G4","wellLocation":{"origin":"bottom","offset":{"z":1,"x":0,"y":0}},"flowRate":274.7}},{"commandType":"moveToAddressableAreaForDropTip","key":"4e4e111e-126d-4d87-8a23-c5bbc5f7de61","params":{"pipetteId":"44539684-2a7a-4443-b90c-9886bb3b0e05","addressableAreaName":"fixedTrash","offset":{"x":0,"y":0,"z":0},"alternateDropLocation":true}},{"commandType":"dropTipInPlace","key":"83650b13-e9e5-41a6-b277-02ab489bbdc2","params":{"pipetteId":"44539684-2a7a-4443-b90c-9886bb3b0e05"}},{"commandType":"pickUpTip","key":"07b4e7f6-0326-4e24-ab3a-aee004da7a33","params":{"pipetteId":"44539684-2a7a-4443-b90c-9886bb3b0e05","labwareId":"42b25c46-8c44-41dc-b7cf-26ed62c1f64e:opentrons/opentrons_96_tiprack_1000ul/1","wellName":"F1"}},{"commandType":"aspirate","key":"1621da63-cddb-4e49-9535-9afcd33ab25e","params":{"pipetteId":"44539684-2a7a-4443-b90c-9886bb3b0e05","volume":75,"labwareId":"09eaa8f8-7a48-4486-8014-6cccc0f389a1:opentrons/nest_12_reservoir_15ml/1","wellName":"A1","wellLocation":{"origin":"bottom","offset":{"z":1,"x":0,"y":0}},"flowRate":274.7}},{"commandType":"dispense","key":"f3c3cb14-344b-4f64-8c2a-aebbfc92790d","params":{"pipetteId":"44539684-2a7a-4443-b90c-9886bb3b0e05","volume":75,"labwareId":"85382d11-cf10-4933-8dae-bd69bbdd1edc:opentrons/nest_96_wellplate_100ul_pcr_full_skirt/2","wellName":"F5","wellLocation":{"origin":"bottom","offset":{"z":1,"x":0,"y":0}},"flowRate":274.7}},{"commandType":"moveToAddressableAreaForDropTip","key":"18fc0753-a503-4e10-ae44-18a78d40e033","params":{"pipetteId":"44539684-2a7a-4443-b90c-9886bb3b0e05","addressableAreaName":"fixedTrash","offset":{"x":0,"y":0,"z":0},"alternateDropLocation":true}},{"commandType":"dropTipInPlace","key":"eb109c83-18fe-4095-aeb8-292d384dbf28","params":{"pipetteId":"44539684-2a7a-4443-b90c-9886bb3b0e05"}},{"commandType":"pickUpTip","key":"da7f2fb5-f352-497f-a025-126b4d5a52cf","params":{"pipetteId":"44539684-2a7a-4443-b90c-9886bb3b0e05","labwareId":"42b25c46-8c44-41dc-b7cf-26ed62c1f64e:opentrons/opentrons_96_tiprack_1000ul/1","wellName":"G1"}},{"commandType":"aspirate","key":"04dfdb13-8246-40b8-847e-640491105b16","params":{"pipetteId":"44539684-2a7a-4443-b90c-9886bb3b0e05","volume":75,"labwareId":"09eaa8f8-7a48-4486-8014-6cccc0f389a1:opentrons/nest_12_reservoir_15ml/1","wellName":"A1","wellLocation":{"origin":"bottom","offset":{"z":1,"x":0,"y":0}},"flowRate":274.7}},{"commandType":"dispense","key":"30c4ec18-b0e7-425e-8d30-867a4627a3e2","params":{"pipetteId":"44539684-2a7a-4443-b90c-9886bb3b0e05","volume":75,"labwareId":"85382d11-cf10-4933-8dae-bd69bbdd1edc:opentrons/nest_96_wellplate_100ul_pcr_full_skirt/2","wellName":"F6","wellLocation":{"origin":"bottom","offset":{"z":1,"x":0,"y":0}},"flowRate":274.7}},{"commandType":"moveToAddressableAreaForDropTip","key":"c1de0c03-3dcd-4010-a91b-905e5d2dde84","params":{"pipetteId":"44539684-2a7a-4443-b90c-9886bb3b0e05","addressableAreaName":"fixedTrash","offset":{"x":0,"y":0,"z":0},"alternateDropLocation":true}},{"commandType":"dropTipInPlace","key":"392af6bb-77b2-49dd-8226-ef87cadb6c59","params":{"pipetteId":"44539684-2a7a-4443-b90c-9886bb3b0e05"}},{"commandType":"pickUpTip","key":"dc3c50b5-1c53-4fe8-b476-5f7cdb7b5da8","params":{"pipetteId":"44539684-2a7a-4443-b90c-9886bb3b0e05","labwareId":"42b25c46-8c44-41dc-b7cf-26ed62c1f64e:opentrons/opentrons_96_tiprack_1000ul/1","wellName":"H1"}},{"commandType":"aspirate","key":"82ff999f-741e-45a3-9308-c356ae6df41f","params":{"pipetteId":"44539684-2a7a-4443-b90c-9886bb3b0e05","volume":75,"labwareId":"09eaa8f8-7a48-4486-8014-6cccc0f389a1:opentrons/nest_12_reservoir_15ml/1","wellName":"A1","wellLocation":{"origin":"bottom","offset":{"z":1,"x":0,"y":0}},"flowRate":274.7}},{"commandType":"dispense","key":"f4ec705b-677d-406d-9704-0dea86d839e6","params":{"pipetteId":"44539684-2a7a-4443-b90c-9886bb3b0e05","volume":75,"labwareId":"85382d11-cf10-4933-8dae-bd69bbdd1edc:opentrons/nest_96_wellplate_100ul_pcr_full_skirt/2","wellName":"G6","wellLocation":{"origin":"bottom","offset":{"z":1,"x":0,"y":0}},"flowRate":274.7}},{"commandType":"moveToAddressableAreaForDropTip","key":"1f7b6f0c-0cef-4d33-9d5b-07bad7dd859c","params":{"pipetteId":"44539684-2a7a-4443-b90c-9886bb3b0e05","addressableAreaName":"fixedTrash","offset":{"x":0,"y":0,"z":0},"alternateDropLocation":true}},{"commandType":"dropTipInPlace","key":"4a8c9340-f64e-4228-841b-46bc27d51dd0","params":{"pipetteId":"44539684-2a7a-4443-b90c-9886bb3b0e05"}},{"commandType":"pickUpTip","key":"65dae455-ceba-45cb-9da9-bde9477a0136","params":{"pipetteId":"44539684-2a7a-4443-b90c-9886bb3b0e05","labwareId":"42b25c46-8c44-41dc-b7cf-26ed62c1f64e:opentrons/opentrons_96_tiprack_1000ul/1","wellName":"A2"}},{"commandType":"aspirate","key":"cb0e8d85-4d3c-4718-8f62-01e09e481410","params":{"pipetteId":"44539684-2a7a-4443-b90c-9886bb3b0e05","volume":75,"labwareId":"09eaa8f8-7a48-4486-8014-6cccc0f389a1:opentrons/nest_12_reservoir_15ml/1","wellName":"A1","wellLocation":{"origin":"bottom","offset":{"z":1,"x":0,"y":0}},"flowRate":274.7}},{"commandType":"dispense","key":"6a23f1f3-e4ad-4d4e-9501-4c2a265dc3e7","params":{"pipetteId":"44539684-2a7a-4443-b90c-9886bb3b0e05","volume":75,"labwareId":"85382d11-cf10-4933-8dae-bd69bbdd1edc:opentrons/nest_96_wellplate_100ul_pcr_full_skirt/2","wellName":"F7","wellLocation":{"origin":"bottom","offset":{"z":1,"x":0,"y":0}},"flowRate":274.7}},{"commandType":"moveToAddressableAreaForDropTip","key":"71cab6fb-d9a5-4165-9d50-3c93c3e9832d","params":{"pipetteId":"44539684-2a7a-4443-b90c-9886bb3b0e05","addressableAreaName":"fixedTrash","offset":{"x":0,"y":0,"z":0},"alternateDropLocation":true}},{"commandType":"dropTipInPlace","key":"d2f2b74c-3a06-4849-9a3e-99bb3c7d0859","params":{"pipetteId":"44539684-2a7a-4443-b90c-9886bb3b0e05"}},{"commandType":"pickUpTip","key":"29341f08-2fea-4589-b493-e82fbc564b7b","params":{"pipetteId":"44539684-2a7a-4443-b90c-9886bb3b0e05","labwareId":"42b25c46-8c44-41dc-b7cf-26ed62c1f64e:opentrons/opentrons_96_tiprack_1000ul/1","wellName":"B2"}},{"commandType":"aspirate","key":"437d0709-107e-47c6-8639-ad3d65df4937","params":{"pipetteId":"44539684-2a7a-4443-b90c-9886bb3b0e05","volume":75,"labwareId":"09eaa8f8-7a48-4486-8014-6cccc0f389a1:opentrons/nest_12_reservoir_15ml/1","wellName":"A1","wellLocation":{"origin":"bottom","offset":{"z":1,"x":0,"y":0}},"flowRate":274.7}},{"commandType":"dispense","key":"b606c19f-3dde-486f-931d-e60fedfc94c5","params":{"pipetteId":"44539684-2a7a-4443-b90c-9886bb3b0e05","volume":75,"labwareId":"85382d11-cf10-4933-8dae-bd69bbdd1edc:opentrons/nest_96_wellplate_100ul_pcr_full_skirt/2","wellName":"E8","wellLocation":{"origin":"bottom","offset":{"z":1,"x":0,"y":0}},"flowRate":274.7}},{"commandType":"moveToAddressableAreaForDropTip","key":"ba3d3981-9d02-4198-ab59-747ae0bd76d8","params":{"pipetteId":"44539684-2a7a-4443-b90c-9886bb3b0e05","addressableAreaName":"fixedTrash","offset":{"x":0,"y":0,"z":0},"alternateDropLocation":true}},{"commandType":"dropTipInPlace","key":"08689d60-baed-48a8-afb3-30404c61b095","params":{"pipetteId":"44539684-2a7a-4443-b90c-9886bb3b0e05"}},{"commandType":"pickUpTip","key":"c6445989-f504-4e09-847c-c1392ee2bd94","params":{"pipetteId":"44539684-2a7a-4443-b90c-9886bb3b0e05","labwareId":"42b25c46-8c44-41dc-b7cf-26ed62c1f64e:opentrons/opentrons_96_tiprack_1000ul/1","wellName":"C2"}},{"commandType":"aspirate","key":"001a9a08-721b-48ef-819f-52441db8c64a","params":{"pipetteId":"44539684-2a7a-4443-b90c-9886bb3b0e05","volume":75,"labwareId":"09eaa8f8-7a48-4486-8014-6cccc0f389a1:opentrons/nest_12_reservoir_15ml/1","wellName":"A1","wellLocation":{"origin":"bottom","offset":{"z":1,"x":0,"y":0}},"flowRate":274.7}},{"commandType":"dispense","key":"787df1c7-220f-499a-862c-86ba2c52b3d5","params":{"pipetteId":"44539684-2a7a-4443-b90c-9886bb3b0e05","volume":75,"labwareId":"85382d11-cf10-4933-8dae-bd69bbdd1edc:opentrons/nest_96_wellplate_100ul_pcr_full_skirt/2","wellName":"F8","wellLocation":{"origin":"bottom","offset":{"z":1,"x":0,"y":0}},"flowRate":274.7}},{"commandType":"moveToAddressableAreaForDropTip","key":"1af06b5b-447b-4f52-83a8-5ec7a28ca74b","params":{"pipetteId":"44539684-2a7a-4443-b90c-9886bb3b0e05","addressableAreaName":"fixedTrash","offset":{"x":0,"y":0,"z":0},"alternateDropLocation":true}},{"commandType":"dropTipInPlace","key":"28a8805a-547f-4f10-bd53-75ba2464a6e5","params":{"pipetteId":"44539684-2a7a-4443-b90c-9886bb3b0e05"}},{"commandType":"pickUpTip","key":"454fb1d6-5a55-4e67-91fd-f514dd031e9d","params":{"pipetteId":"44539684-2a7a-4443-b90c-9886bb3b0e05","labwareId":"42b25c46-8c44-41dc-b7cf-26ed62c1f64e:opentrons/opentrons_96_tiprack_1000ul/1","wellName":"D2"}},{"commandType":"aspirate","key":"860f4bf9-b1ac-4d3a-982d-a5f3896ed46a","params":{"pipetteId":"44539684-2a7a-4443-b90c-9886bb3b0e05","volume":75,"labwareId":"09eaa8f8-7a48-4486-8014-6cccc0f389a1:opentrons/nest_12_reservoir_15ml/1","wellName":"A1","wellLocation":{"origin":"bottom","offset":{"z":1,"x":0,"y":0}},"flowRate":274.7}},{"commandType":"dispense","key":"3c0cb90d-11f6-4a69-bff5-61d6ffcf1f7c","params":{"pipetteId":"44539684-2a7a-4443-b90c-9886bb3b0e05","volume":75,"labwareId":"85382d11-cf10-4933-8dae-bd69bbdd1edc:opentrons/nest_96_wellplate_100ul_pcr_full_skirt/2","wellName":"G8","wellLocation":{"origin":"bottom","offset":{"z":1,"x":0,"y":0}},"flowRate":274.7}},{"commandType":"moveToAddressableAreaForDropTip","key":"8dd70280-f5ab-46af-be0e-7304f63a04c2","params":{"pipetteId":"44539684-2a7a-4443-b90c-9886bb3b0e05","addressableAreaName":"fixedTrash","offset":{"x":0,"y":0,"z":0},"alternateDropLocation":true}},{"commandType":"dropTipInPlace","key":"f30f1ce5-290a-4ac1-94b3-9c2b6605f05c","params":{"pipetteId":"44539684-2a7a-4443-b90c-9886bb3b0e05"}},{"commandType":"pickUpTip","key":"f7370d72-04f4-409f-a32b-08efc488edfb","params":{"pipetteId":"44539684-2a7a-4443-b90c-9886bb3b0e05","labwareId":"42b25c46-8c44-41dc-b7cf-26ed62c1f64e:opentrons/opentrons_96_tiprack_1000ul/1","wellName":"E2"}},{"commandType":"aspirate","key":"59dfc84f-d670-436d-a289-c9e78ab77305","params":{"pipetteId":"44539684-2a7a-4443-b90c-9886bb3b0e05","volume":375,"labwareId":"09eaa8f8-7a48-4486-8014-6cccc0f389a1:opentrons/nest_12_reservoir_15ml/1","wellName":"A4","wellLocation":{"origin":"bottom","offset":{"z":1,"x":0,"y":0}},"flowRate":274.7}},{"commandType":"dispense","key":"5e044998-558a-457c-9044-06b183c770a3","params":{"pipetteId":"44539684-2a7a-4443-b90c-9886bb3b0e05","volume":75,"labwareId":"85382d11-cf10-4933-8dae-bd69bbdd1edc:opentrons/nest_96_wellplate_100ul_pcr_full_skirt/2","wellName":"H4","wellLocation":{"origin":"bottom","offset":{"z":1,"x":0,"y":0}},"flowRate":274.7}},{"commandType":"dispense","key":"0b8a1020-ea48-41b4-9b2d-874a96e865a4","params":{"pipetteId":"44539684-2a7a-4443-b90c-9886bb3b0e05","volume":75,"labwareId":"85382d11-cf10-4933-8dae-bd69bbdd1edc:opentrons/nest_96_wellplate_100ul_pcr_full_skirt/2","wellName":"B5","wellLocation":{"origin":"bottom","offset":{"z":1,"x":0,"y":0}},"flowRate":274.7}},{"commandType":"dispense","key":"7590e41c-fdb9-4ec4-9ae2-7fdad442d54e","params":{"pipetteId":"44539684-2a7a-4443-b90c-9886bb3b0e05","volume":75,"labwareId":"85382d11-cf10-4933-8dae-bd69bbdd1edc:opentrons/nest_96_wellplate_100ul_pcr_full_skirt/2","wellName":"G5","wellLocation":{"origin":"bottom","offset":{"z":1,"x":0,"y":0}},"flowRate":274.7}},{"commandType":"dispense","key":"786f85bd-678a-4a33-a4c6-5c4700ff4d09","params":{"pipetteId":"44539684-2a7a-4443-b90c-9886bb3b0e05","volume":75,"labwareId":"85382d11-cf10-4933-8dae-bd69bbdd1edc:opentrons/nest_96_wellplate_100ul_pcr_full_skirt/2","wellName":"G7","wellLocation":{"origin":"bottom","offset":{"z":1,"x":0,"y":0}},"flowRate":274.7}},{"commandType":"dispense","key":"63e9bfd9-9fe5-4206-b1a2-8ff3ceb9b781","params":{"pipetteId":"44539684-2a7a-4443-b90c-9886bb3b0e05","volume":75,"labwareId":"85382d11-cf10-4933-8dae-bd69bbdd1edc:opentrons/nest_96_wellplate_100ul_pcr_full_skirt/2","wellName":"H8","wellLocation":{"origin":"bottom","offset":{"z":1,"x":0,"y":0}},"flowRate":274.7}},{"commandType":"moveToAddressableAreaForDropTip","key":"904aa00d-a8ef-4772-b5b5-795f3edbbf5c","params":{"pipetteId":"44539684-2a7a-4443-b90c-9886bb3b0e05","addressableAreaName":"fixedTrash","offset":{"x":0,"y":0,"z":0},"alternateDropLocation":true}},{"commandType":"dropTipInPlace","key":"97439319-cc38-475a-98e7-e37eaad6e83b","params":{"pipetteId":"44539684-2a7a-4443-b90c-9886bb3b0e05"}}],"commandAnnotationSchemaId":"opentronsCommandAnnotationSchemaV1","commandAnnotations":[]}